ib1/directory/__init__.py
ib1/directory/certificates.py
ib1/directory/cli.py
ib1/directory/der.py
ib1/directory/exceptions.py
ib1/directory/extensions.py
ib1/directory/py.typed
ib1/directory/utils.py
ib1_directory-0.9.2.dist-info/LICENSE
ib1_directory-0.9.2.dist-info/METADATA
ib1_directory-0.9.2.dist-info/WHEEL
ib1_directory-0.9.2.dist-info/entry_points.txt
ib1_directory-0.9.2.dist-info/RECORD
