Metadata-Version: 2.1
Name: ib1-directory
Version: 0.9.2
Summary: A library to simplify working with the IB1 Trust Framework directory
Author: Kip Parker
Author-email: kip.parker@icebreakerone.org
Requires-Python: >=3.10,<4.0
Classifier: Programming Language :: Python :: 3
Classifier: Programming Language :: Python :: 3.10
Classifier: Programming Language :: Python :: 3.11
Classifier: Programming Language :: Python :: 3.12
Requires-Dist: asn1crypto (>=1.5.1,<2.0.0)
Requires-Dist: click (>=8.1.7,<9.0.0)
Requires-Dist: cryptography (>=43.0.1,<44.0.0)
